SigmaKokiPy/SK_Controller.py
SigmaKokiPy/SK_SHOT.py
SigmaKokiPy/__init__.py
SigmaKokiPy/clsStageAxisSHOT.py
SigmaKokiPy-0.0.3.dist-info/LICENCE
SigmaKokiPy-0.0.3.dist-info/METADATA
SigmaKokiPy-0.0.3.dist-info/WHEEL
SigmaKokiPy-0.0.3.dist-info/top_level.txt
SigmaKokiPy-0.0.3.dist-info/RECORD
